claude_metadata_chatbot/__init__.py
claude_metadata_chatbot-0.0.2.dist-info/LICENSE
claude_metadata_chatbot-0.0.2.dist-info/METADATA
claude_metadata_chatbot-0.0.2.dist-info/WHEEL
claude_metadata_chatbot-0.0.2.dist-info/top_level.txt
claude_metadata_chatbot-0.0.2.dist-info/RECORD
